reade/__init__.py
reade-0.1.dist-info/METADATA
reade-0.1.dist-info/WHEEL
reade-0.1.dist-info/top_level.txt
reade-0.1.dist-info/RECORD
